pennylane_noisy_qubit/__init__.py
pennylane_noisy_qubit/noisy_qubit.py
pennylane_noisy_qubit-0.4.dist-info/LICENSE
pennylane_noisy_qubit-0.4.dist-info/METADATA
pennylane_noisy_qubit-0.4.dist-info/WHEEL
pennylane_noisy_qubit-0.4.dist-info/entry_points.txt
pennylane_noisy_qubit-0.4.dist-info/top_level.txt
pennylane_noisy_qubit-0.4.dist-info/RECORD
